{
    "post": {
        "summary": "Forgot password",
        "tags": ["Auth"],
        "requestBody": {
            "$ref": "../../requests/forgot-password.json"
        },
        "responses": {
            "200": {
                "description": "Token sent to your email"
            },
            "400": {
                "$ref": "../../responses/validation-error.json"
            },
            "default": {
                "$ref": "../../responses/unexpected-error.json"
            }
        }
    }
}
